django_test_tools/__init__.py
django_test_tools/app_manager.py
django_test_tools/apps.py
django_test_tools/assert_utils.py
django_test_tools/excel.py
django_test_tools/exceptions.py
django_test_tools/file_utils.py
django_test_tools/mixins.py
django_test_tools/urls.py
django_test_tools/utils.py
django_test_tools/_legacy/__init__.py
django_test_tools/_legacy/assert_utils.py
django_test_tools/_legacy/checks.py
django_test_tools/_legacy/handlers.py
django_test_tools/_legacy/mixins.py
django_test_tools/_legacy/utils.py
django_test_tools/_legacy/doc_utils/__init__.py
django_test_tools/_legacy/doc_utils/folder_structure.py
django_test_tools/_legacy/management/__init__.py
django_test_tools/_legacy/management/commands/__init__.py
django_test_tools/_legacy/management/commands/generate_factories.py
django_test_tools/_legacy/management/commands/git_report.py
django_test_tools/_legacy/management/commands/parse_qc_files.py
django_test_tools/_legacy/tests/__init__.py
django_test_tools/generators/__init__.py
django_test_tools/generators/crud_generator.py
django_test_tools/generators/enums.py
django_test_tools/generators/model_generator.py
django_test_tools/generators/model_test_gen.py
django_test_tools/generators/models.py
django_test_tools/generators/serializer_gen.py
django_test_tools/generators/handlers/__init__.py
django_test_tools/generators/handlers/factory_boy_handlers.py
django_test_tools/management/__init__.py
django_test_tools/management/commands/__init__.py
django_test_tools/management/commands/app_to_json.py
django_test_tools/management/commands/convert_to_json.py
django_test_tools/management/commands/generate_factories.py
django_test_tools/management/commands/generate_model_test_cases.py
django_test_tools/management/commands/generate_serializers.py
django_test_tools/management/commands/generate_serializers_tests.py
django_test_tools/re/__init__.py
django_test_tools/re/regexp.py
django_test_tools/templates/django_test_tools/app_index.rst.j2
django_test_tools-2.2.3.dist-info/AUTHORS.rst
django_test_tools-2.2.3.dist-info/LICENSE
django_test_tools-2.2.3.dist-info/METADATA
django_test_tools-2.2.3.dist-info/WHEEL
django_test_tools-2.2.3.dist-info/top_level.txt
django_test_tools-2.2.3.dist-info/RECORD
