Metadata-Version: 2.1
Name: django-test-tools
Version: 2.2.3
Summary: Simple tests tools to make testing faster and easier.
Home-page: https://github.com/luiscberrocal/django-test-tools
Author: Luis Carlos Berrocal
Author-email: luis.berrocal.1942@gmail.com
License: MIT
Keywords: django-test-tools
Classifier: Development Status :: 5 - Production/Stable
Classifier: Environment :: Web Environment
Classifier: Framework :: Django
Classifier: Framework :: Django :: 3.2
Classifier: Framework :: Django :: 4.2
Classifier: Intended Audience :: Developers
Classifier: License :: OSI Approved :: MIT License
Classifier: Natural Language :: English
Classifier: Programming Language :: Python :: 3.8
Classifier: Programming Language :: Python :: 3.9
Classifier: Programming Language :: Python :: 3.10
License-File: LICENSE
License-File: AUTHORS.rst
Requires-Dist: Django
Requires-Dist: Jinja2 (>=3.0.1)
Requires-Dist: openpyxl (>=3.0.7)
Requires-Dist: requests (>=2.26.0)
Requires-Dist: pydantic (<2.0,>=1.10)
